{"cameraMode":{"drawMode":0,"name":"Shaded","section":"Shading Mode"},"sceneLighting":false,"audioPlay":false,"sceneViewState":{"m_AlwaysRefresh":false,"showFog":true,"showSkybox":false,"showFlares":true,"showImageEffects":true,"showParticleSystems":true,"showVisualEffectGraphs":true,"m_FxEnabled":true},"in2DMode":false,"pivot":{"x":-25.935461044311525,"y":1.869922161102295,"z":-86.55197143554688},"rotation":{"x":-0.4553547203540802,"y":-0.012834412977099419,"z":0.006536845583468676,"w":-0.8902254700660706},"size":7.833426475524902,"orthographic":false}